logplot
