Metadata-Version: 1.1
Name: logplot
Version: 1.0.4
Summary: Awesome plots from custom logs
Home-page: https://github.com/jerry-git/logplot
Author: Jerry Pussinen
Author-email: jerry.pussinen@gmail.com
License: UNKNOWN
Platform: UNKNOWN
Classifier: License :: OSI Approved :: MIT License
Classifier: Programming Language :: Python
Classifier: Programming Language :: Python :: 3
Classifier: Programming Language :: Python :: 3.5
Classifier: Programming Language :: Python :: 3.6
Classifier: Programming Language :: Python :: 3.7
